pysmt/__init__.py
pysmt/__main__.py
pysmt/configuration.py
pysmt/constants.py
pysmt/decorators.py
pysmt/environment.py
pysmt/exceptions.py
pysmt/factory.py
pysmt/fnode.py
pysmt/formula.py
pysmt/logics.py
pysmt/operators.py
pysmt/oracles.py
pysmt/parsing.py
pysmt/printers.py
pysmt/rewritings.py
pysmt/shortcuts.py
pysmt/simplifier.py
pysmt/substituter.py
pysmt/type_checker.py
pysmt/typing.py
pysmt/utils.py
pysmt/cmd/__init__.py
pysmt/cmd/check_version.py
pysmt/cmd/install.py
pysmt/cmd/shell.py
pysmt/cmd/installers/__init__.py
pysmt/cmd/installers/base.py
pysmt/cmd/installers/bdd.py
pysmt/cmd/installers/btor.py
pysmt/cmd/installers/cvcfive.py
pysmt/cmd/installers/cvcfour.py
pysmt/cmd/installers/msat.py
pysmt/cmd/installers/pico.py
pysmt/cmd/installers/yices.py
pysmt/cmd/installers/z3.py
pysmt/smtlib/__init__.py
pysmt/smtlib/annotations.py
pysmt/smtlib/commands.py
pysmt/smtlib/printers.py
pysmt/smtlib/script.py
pysmt/smtlib/solver.py
pysmt/smtlib/utils.py
pysmt/smtlib/parser/__init__.py
pysmt/smtlib/parser/parser.py
pysmt/solvers/__init__.py
pysmt/solvers/bdd.py
pysmt/solvers/btor.py
pysmt/solvers/cvcfive.py
pysmt/solvers/cvcfour.py
pysmt/solvers/eager.py
pysmt/solvers/interpolation.py
pysmt/solvers/msat.py
pysmt/solvers/options.py
pysmt/solvers/pico.py
pysmt/solvers/portfolio.py
pysmt/solvers/qelim.py
pysmt/solvers/smtlib.py
pysmt/solvers/solver.py
pysmt/solvers/yices.py
pysmt/solvers/z3.py
pysmt/test/__init__.py
pysmt/test/examples.py
pysmt/test/test_array.py
pysmt/test/test_back.py
pysmt/test/test_bdd.py
pysmt/test/test_bv.py
pysmt/test/test_bv_simplification.py
pysmt/test/test_cnf.py
pysmt/test/test_configuration.py
pysmt/test/test_constants.py
pysmt/test/test_cvc_quantifiers.py
pysmt/test/test_dwf.py
pysmt/test/test_eager_model.py
pysmt/test/test_env.py
pysmt/test/test_euf.py
pysmt/test/test_formula.py
pysmt/test/test_hr_parsing.py
pysmt/test/test_imports.py
pysmt/test/test_int.py
pysmt/test/test_interpolation.py
pysmt/test/test_lira.py
pysmt/test/test_logics.py
PySMT-0.9.6.dist-info/LICENSE
PySMT-0.9.6.dist-info/METADATA
PySMT-0.9.6.dist-info/NOTICE
PySMT-0.9.6.dist-info/WHEEL
PySMT-0.9.6.dist-info/entry_points.txt
PySMT-0.9.6.dist-info/top_level.txt
PySMT-0.9.6.dist-info/RECORD
