Metadata-Version: 1.0
Name: PySMT
Version: 0.9.6
Summary: A solver-agnostic library for SMT Formulae manipulation and solving
Home-page: http://www.pysmt.org
Author: PySMT Team
Author-email: info@pysmt.org
License: APACHE
Platform: UNKNOWN
